README.txt
setup.cfg
setup.py
docs/HISTORY.txt
import/formular.zexp
zopyx/__init__.py
zopyx.smartprintng.lite.egg-info/PKG-INFO
zopyx.smartprintng.lite.egg-info/SOURCES.txt
zopyx.smartprintng.lite.egg-info/dependency_links.txt
zopyx.smartprintng.lite.egg-info/entry_points.txt
zopyx.smartprintng.lite.egg-info/namespace_packages.txt
zopyx.smartprintng.lite.egg-info/not-zip-safe
zopyx.smartprintng.lite.egg-info/requires.txt
zopyx.smartprintng.lite.egg-info/top_level.txt
zopyx/smartprintng/__init__.py
zopyx/smartprintng/lite/__init__.py
zopyx/smartprintng/lite/configure.zcml
zopyx/smartprintng/lite/header.txt
zopyx/smartprintng/lite/logger.py
zopyx/smartprintng/lite/meta.zcml
zopyx/smartprintng/lite/resources.py
zopyx/smartprintng/lite/zcml.py
zopyx/smartprintng/lite/browser/__init__.py
zopyx/smartprintng/lite/browser/compatible.py
zopyx/smartprintng/lite/browser/configure.zcml
zopyx/smartprintng/lite/browser/document.py
zopyx/smartprintng/lite/browser/document_raw.pt
zopyx/smartprintng/lite/browser/newsitem.py
zopyx/smartprintng/lite/browser/newsitem_raw.pt
zopyx/smartprintng/lite/browser/pdf.py
zopyx/smartprintng/lite/browser/sorting.py
zopyx/smartprintng/lite/browser/topic.py
zopyx/smartprintng/lite/browser/transformation.py
zopyx/smartprintng/lite/browser/util.py
zopyx/smartprintng/lite/browser/resources/pdf_template.pt
zopyx/smartprintng/lite/browser/resources/pfg_pdf_template.pt
zopyx/smartprintng/lite/browser/resources/styles.css
zopyx/smartprintng/lite/browser/resources/hyphenation/af.hyp
zopyx/smartprintng/lite/browser/resources/hyphenation/be.hyp
zopyx/smartprintng/lite/browser/resources/hyphenation/bg.hyp
zopyx/smartprintng/lite/browser/resources/hyphenation/cs.hyp
zopyx/smartprintng/lite/browser/resources/hyphenation/da.hyp
zopyx/smartprintng/lite/browser/resources/hyphenation/de.hyp
zopyx/smartprintng/lite/browser/resources/hyphenation/en.hyp
zopyx/smartprintng/lite/browser/resources/hyphenation/et.hyp
zopyx/smartprintng/lite/browser/resources/hyphenation/fr.hyp
zopyx/smartprintng/lite/browser/resources/hyphenation/hr.hyp
zopyx/smartprintng/lite/browser/resources/hyphenation/ia.hyp
zopyx/smartprintng/lite/browser/resources/hyphenation/it.hyp
zopyx/smartprintng/lite/browser/resources/hyphenation/lv.hyp
zopyx/smartprintng/lite/browser/resources/hyphenation/mn.hyp
zopyx/smartprintng/lite/browser/resources/hyphenation/ro.hyp
