Metadata-Version: 1.0
Name: zopyx.smartprintng.lite
Version: 1.0.3
Summary: Produce & Publish Lite
Home-page: http://pypi.python.org/pypi/zopyx.smartprintng.lite
Author: Andreas Jung
Author-email: info@zopyx.com
License: GPL
Keywords: PDF Python Zope Plone Produce Publish
Platform: UNKNOWN
Classifier: Programming Language :: Python
Classifier: Development Status :: 5 - Production/Stable
Classifier: Topic :: Software Development :: Libraries :: Python Modules
